gocats/__init__.py
gocats/__main__.py
gocats/_version.py
gocats/dag.py
gocats/gocats.py
gocats/godag.py
gocats/ontologyparser.py
gocats/subdag.py
gocats/tools.py
tests/__init__.py
tests/test_dummy.py
tests/test_manuscript3.py
GOcats-1.2.1.dist-info/LICENSE
GOcats-1.2.1.dist-info/METADATA
GOcats-1.2.1.dist-info/WHEEL
GOcats-1.2.1.dist-info/top_level.txt
GOcats-1.2.1.dist-info/RECORD
