Metadata-Version: 2.1
Name: GOcats
Version: 1.2.1
Summary: A tool for categorizing Gene Ontology into subgraphs of user-defined emergent concepts
Home-page: https://github.com/MoseleyBioinformaticsLab/GOcats
Author: Eugene W. Hinderer III
Author-email: ehinderer01@gmail.com
License: The Clear BSD License
Keywords: biomedical ontology analysis
Classifier: Development Status :: 3 - Alpha
Classifier: Intended Audience :: Science/Research
Classifier: Topic :: Scientific/Engineering :: Information Analysis
Classifier: License :: OSI Approved :: BSD License
Classifier: Programming Language :: Python :: 3
Classifier: Programming Language :: Python :: 3.3
Classifier: Programming Language :: Python :: 3.4
Classifier: Programming Language :: Python :: 3.5
License-File: LICENSE
Requires-Dist: docopt
Requires-Dist: jsonpickle
